{"assets/png/celerry-mockup.png":["assets/png/celerry-mockup.png"],"assets/png/data-scientist-1.png":["assets/png/data-scientist-1.png"],"assets/png/deprofile-mockup.png":["assets/png/deprofile-mockup.png"],"assets/png/deqr-mockup.png":["assets/png/deqr-mockup.png"],"assets/png/devfest-1.png":["assets/png/devfest-1.png"],"assets/png/devin-mockup.png":["assets/png/devin-mockup.png"],"assets/png/fcd-mockup.png":["assets/png/fcd-mockup.png"],"assets/png/gadai-express-mockup.png":["assets/png/gadai-express-mockup.png"],"assets/png/ikis.png":["assets/png/ikis.png"],"assets/png/lks-kab.png":["assets/png/lks-kab.png"],"assets/png/lks-prov.png":["assets/png/lks-prov.png"],"assets/png/makerindo-mockup.png":["assets/png/makerindo-mockup.png"],"assets/png/makerindo.png":["assets/png/makerindo.png"],"assets/png/matchapp-mockup.png":["assets/png/matchapp-mockup.png"],"assets/png/mpr-ri-4-pilar-1.png":["assets/png/mpr-ri-4-pilar-1.png"],"assets/png/scf-ai.png":["assets/png/scf-ai.png"],"assets/png/toko-saya-mockup.png":["assets/png/toko-saya-mockup.png"],"assets/svg/codeigniter.svg":["assets/svg/codeigniter.svg"],"assets/svg/dartlang-icon.svg":["assets/svg/dartlang-icon.svg"],"assets/svg/dotnet-icon.svg":["assets/svg/dotnet-icon.svg"],"assets/svg/dotnet-logo.svg":["assets/svg/dotnet-logo.svg"],"assets/svg/firebase-icon.svg":["assets/svg/firebase-icon.svg"],"assets/svg/flutterio-icon.svg":["assets/svg/flutterio-icon.svg"],"assets/svg/github-icon-1.svg":["assets/svg/github-icon-1.svg"],"assets/svg/github-mark-white.svg":["assets/svg/github-mark-white.svg"],"assets/svg/hexagon.svg":["assets/svg/hexagon.svg"],"assets/svg/icons8-instagram.svg":["assets/svg/icons8-instagram.svg"],"assets/svg/icons8-linkedin.svg":["assets/svg/icons8-linkedin.svg"],"assets/svg/java-icon.svg":["assets/svg/java-icon.svg"],"assets/svg/laravel-2.svg":["assets/svg/laravel-2.svg"],"assets/svg/office-2.svg":["assets/svg/office-2.svg"],"assets/svg/python-5.svg":["assets/svg/python-5.svg"],"assets/svg/skewed.svg":["assets/svg/skewed.svg"],"packages/cupertino_icons/assets/CupertinoIcons.ttf":["packages/cupertino_icons/assets/CupertinoIcons.ttf"]}